serp_geo_mcp/__init__.py
serp_geo_mcp/server.py
serp_geo_mcp-0.1.0.dist-info/METADATA
serp_geo_mcp-0.1.0.dist-info/WHEEL
serp_geo_mcp-0.1.0.dist-info/top_level.txt
serp_geo_mcp-0.1.0.dist-info/RECORD
