Metadata-Version: 2.4
Name: serp-geo-mcp
Version: 0.1.0
Summary: A geo-location based MCP server using SerpApi
Author: anil kumar
Author-email: anilkumarbaatula@gmail.com
Classifier: Programming Language :: Python :: 3
Classifier: License :: OSI Approved :: MIT License
Requires-Python: >=3.7
Requires-Dist: requests
Requires-Dist: python-dotenv
Requires-Dist: fastmcp
Dynamic: author
Dynamic: author-email
Dynamic: classifier
Dynamic: description-content-type
Dynamic: requires-dist
Dynamic: requires-python
Dynamic: summary
